nginx_secure_links/__init__.py
nginx_secure_links/settings.py
nginx_secure_links/storages.py
nginx_secure_links/utils.py
nginx_secure_links/management/__init__.py
nginx_secure_links/management/commands/__init__.py
nginx_secure_links/management/commands/secure_links_gen_signed.py
nginx_secure_links/management/commands/secure_links_nginx_location.py
nginx_secure_links/templates/nginx_secure_links/locations.conf
django_nginx_secure_links-0.0.9.dist-info/LICENSE
django_nginx_secure_links-0.0.9.dist-info/METADATA
django_nginx_secure_links-0.0.9.dist-info/WHEEL
django_nginx_secure_links-0.0.9.dist-info/top_level.txt
django_nginx_secure_links-0.0.9.dist-info/RECORD
